alignreg/__init__.py
alignreg/augment.py
alignreg/regularization.py
alignreg/tf_training.py
alignreg/torch_training.py
alignreg-1.0.1.dist-info/LICENSE
alignreg-1.0.1.dist-info/METADATA
alignreg-1.0.1.dist-info/WHEEL
alignreg-1.0.1.dist-info/top_level.txt
alignreg-1.0.1.dist-info/RECORD
